trimetpy.py
trimetpy-0.2.2.dist-info/METADATA
trimetpy-0.2.2.dist-info/WHEEL
trimetpy-0.2.2.dist-info/top_level.txt
trimetpy-0.2.2.dist-info/RECORD
